hassl/__init__.py
hassl/cli.py
hassl/ast/__init__.py
hassl/ast/nodes.py
hassl/codegen/__init__.py
hassl/codegen/generate.py
hassl/codegen/init.py
hassl/codegen/package.py
hassl/codegen/rules_min.py
hassl/codegen/yaml_emit.py
hassl/parser/__init__.py
hassl/parser/hassl.lark
hassl/parser/loader.py
hassl/parser/transform.py
hassl/semantics/__init__.py
hassl/semantics/analyzer.py
hassl/semantics/domains.py
hassl-0.3.2.dist-info/licenses/LICENSE
hassl-0.3.2.dist-info/METADATA
hassl-0.3.2.dist-info/WHEEL
hassl-0.3.2.dist-info/entry_points.txt
hassl-0.3.2.dist-info/top_level.txt
hassl-0.3.2.dist-info/RECORD
