Metadata-Version: 2.4
Name: hassl
Version: 0.3.2
Summary: HASSL: Home Assistant Simple Scripting Language
Home-page: https://github.com/adanowitz/hassl
Author: adanowitz
Author-email: adanowitz@gmail.com
Requires-Python: >=3.11
License-File: LICENSE
Requires-Dist: lark-parser
Requires-Dist: jinja2
Requires-Dist: pyyaml
Dynamic: license-file
